SeekWell-0.1.dist-info/DESCRIPTION.rst
SeekWell-0.1.dist-info/METADATA
SeekWell-0.1.dist-info/RECORD
SeekWell-0.1.dist-info/WHEEL
SeekWell-0.1.dist-info/metadata.json
SeekWell-0.1.dist-info/top_level.txt
seekwell/__init__.py
seekwell/columns.py
seekwell/database.py
seekwell/export.py
seekwell/records.py
seekwell/table.py
