Metadata-Version: 2.0
Name: SeekWell
Version: 0.1
Summary: SQL for Data Analysts
Home-page: https://github.com/mcleonard/seekwell
Author: Mat Leonard
Author-email: leonard.mat@gmail.com
License: LICENSE.txt
Platform: UNKNOWN
Requires: sqlalchemy
Requires: terminaltables
